{"stats":{"minecraft:killed":{"minecraft:zombie":1},"minecraft:custom":{"minecraft:jump":157,"minecraft:time_since_rest":4885,"minecraft:leave_game":1,"minecraft:crouch_one_cm":667,"minecraft:sprint_one_cm":14697,"minecraft:play_time":4885,"minecraft:walk_on_water_one_cm":1314,"minecraft:time_since_death":4885,"minecraft:walk_one_cm":6810,"minecraft:sneak_time":364,"minecraft:total_world_time":5582,"minecraft:walk_under_water_one_cm":769,"minecraft:mob_kills":1,"minecraft:swim_one_cm":5660,"minecraft:fall_one_cm":1521,"minecraft:drop":1,"minecraft:fly_one_cm":48294},"minecraft:dropped":{"minecraft:cobblestone":64},"minecraft:used":{"minecraft:golden_apple":2,"minecraft:bow":14}},"DataVersion":3218}